ome_arrow/__init__.py
ome_arrow/_version.py
ome_arrow/core.py
ome_arrow/export.py
ome_arrow/ingest.py
ome_arrow/meta.py
ome_arrow/transform.py
ome_arrow/utils.py
ome_arrow/view.py
ome_arrow-0.0.2.dist-info/licenses/LICENSE
ome_arrow-0.0.2.dist-info/METADATA
ome_arrow-0.0.2.dist-info/WHEEL
ome_arrow-0.0.2.dist-info/top_level.txt
ome_arrow-0.0.2.dist-info/RECORD
