Metadata-Version: 2.4
Name: ome-arrow
Version: 0.0.2
Summary: Using OME specifications with Apache Arrow for fast, queryable, and language agnostic bioimage data.
Author: Dave Bunten
Classifier: Programming Language :: Python :: 3 :: Only
Classifier: Programming Language :: Python :: 3.11
Classifier: Programming Language :: Python :: 3.12
Classifier: Programming Language :: Python :: 3.13
Classifier: Programming Language :: Python :: 3.14
Requires-Python: >=3.11
License-File: LICENSE
Requires-Dist: bioio>=3
Requires-Dist: bioio-ome-tiff>=1.4
Requires-Dist: bioio-ome-zarr>=3.0.3
Requires-Dist: bioio-tifffile>=1.3
Requires-Dist: fire>=0.7
Requires-Dist: ipywidgets>=8.1.8
Requires-Dist: jupyterlab-widgets>=3.0.16
Requires-Dist: matplotlib>=3.10.7
Requires-Dist: numpy>=2.2.6
Requires-Dist: pandas>=2.2.3
Requires-Dist: pillow>=12
Requires-Dist: pyarrow>=22
Requires-Dist: pyvista>=0.46.4
Requires-Dist: trame>=3.12
Requires-Dist: trame-vtk>=2.10
Requires-Dist: trame-vuetify>=3.1
Dynamic: license-file
